<?xml version="1.0" encoding="UTF-8"?>
<Entity>
	<Identity>
		<Name>Mentos</Name>
	</Identity>
	
	<Cost>
		<Aladdium>2000</Aladdium>
		<Food>5</Food>
		<SpawnTime>160</SpawnTime>
	</Cost>
	
	<FactionMembership/>
	
	<Kamikaze>
		<Radius>10</Radius>
		<Damage>400</Damage>
		<Targets>
			<Target>DietCoke</Target>
		</Targets>
	</Kamikaze>
	
	<Health>
		<MaxValue>160</MaxValue>
		<ArmorType>Supernatural</ArmorType>
		<Armor>4</Armor>
	</Health>
	
	<Mobile>
		<Speed>3</Speed>
	</Mobile>
	
	<Spatial>
		<CollisionLayer>Ground</CollisionLayer>
		<Size>
			<Width>1</Width>
			<Height>1</Height>
		</Size>
	</Spatial>

	<Sprite/>
	
	<Vision>
		<Range>3</Range>
	</Vision>
	
	<Tags/>
</Entity>